{
    "Amazon-AWS-Auto-Scaling": "External", 
    "Amazon-DynamoDB-Object-Mapper": "External", 
    "Dexter": "AndroidUtil", 
    "Amazon-Ads": "Advertising", 
    "Facebook-Audience": "Advertising",
    "SQLCipher": "Util", 
    "Leadbolt": "Advertising", 
    "Hunt-mobile-advertising": "Advertising", 
    "Google-Play-Services-Gcm": "AndroidDev", 
    "piwik": "Analytics", 
    "drawbridge": "Advertising", 
    "Syrup": "Advertising", 
    "Amazon-Simple-Queue-Service-(SQS)": "External", 
    "BeaconsInSpace": "External", 
    "vpon": "Advertising", 
    "Tapjoy": "Advertising", 
    "Amazon-Machine-Learning": "External", 
    "Amazon-Elastic-Compute-Cloud-(EC2)": "External", 
    "NetCipher-volley": "Network", 
    "SQLBrite": "Util", 
    "MessagePack": "Util", 
    "Digits": "External", 
    "JSch": "Network", 
    "AdFalcon": "Advertising", 
    "QuickBlox-location": "External", 
    "MoPub-native-video": "Advertising", 
    "Google-Play-Services-Wearable": "AndroidDev", 
    "Tremor-Video": "Advertising", 
    "MoPub-banner": "Advertising", 
    "JTwitter": "SocialMedia", 
    "Google-Play-Services-Base": "AndroidDev", 
    "Amazon-Cognito-Sync": "External", 
    "Login-with-Amazon": "External", 
    "Vungle": "Advertising", 
    "EventBus": "AndroidUtil", 
    "NetCipher-okhttp3": "Network", 
    "Facebook-App-Links": "SocialMedia", 
    "okio": "Extension", 
    "Google-Play-Services-Location": "AndroidDev", 
    "Google-Play-Services-Drive": "AndroidDev", 
    "Amazon-Cognito-Identity-Provider": "External", 
    "Google-Play-Services-Appindexing": "AndroidDev", 
    "Mixpanel": "Analytics", 
    "leakcanary": "Util", 
    "Amazon-Kinesis-Streams": "External", 
    "Airpush-(Standard)": "Advertising", 
    "Google-Play-Services-Cast-Framework": "AndroidDev", 
    "Parse": "External", 
    "Google-Play-Services-Measurement": "AndroidDev", 
    "Google-Play-Services-Basement": "AndroidDev", 
    "Amazon-Cloud-Drive": "External", 
    "RxAndroidBle": "Network", 
    "Google-Play-Services-Tagmanager-Api": "AndroidDev", 
    "Airpush-(Bundle1)": "Advertising", 
    "CacheWord": "AndroidUtil", 
    "Google-Play-Services-Ads": "AndroidDev", 
    "Google-Play-Services-Games": "AndroidDev", 
    "Amazon-Mobile-Associates": "External", 
    "OneDrive": "External", 
    "Google-Play-Services-Maps": "AndroidDev", 
    "AppFlood": "Advertising", 
    "ADResult": "Advertising", 
    "domob": "Advertising", 
    "Google-Play-Services-Ads-Lite": "AndroidDev", 
    "Amazon-Lex": "External", 
    "Mobfox": "Advertising", 
    "Panic": "AndroidUtil", 
    "Google-Play-Services-Identity": "AndroidDev", 
    "Tencent-GDT": "Advertising", 
    "Google-Play-Services-Analytics": "AndroidDev", 
    "uCrop": "Image", 
    "Bolts": "AndroidUtil", 
    "AppsFlyer": "Analytics", 
    "Sensey": "AndroidUtil", 
    "Amazon-Pinpoint": "External", 
    "Google-Play-Services-Tagmanager": "AndroidDev", 
    "Brightroll": "Advertising", 
    "jsoup": "Util", 
    "Google-Play-Services-Appstate": "AndroidDev", 
    "Facebook": "SocialMedia", 
    "Twilio": "External", 
    "MapBox": "External", 
    "mAdserve": "Advertising", 
    "Amazon-Simple-Notification-Service-(SNS)": "External", 
    "AppAuth": "Network", 
    "ScribeJava-Core": "Network", 
    "Amazon-Device-Messaging": "External", 
    "Amazon-DynamoDB": "External", 
    "Google-Play-Services-Clearcut": "AndroidDev", 
    "NetCipher": "Network", 
    "Nine-Old-Androids": "AndroidUtil", 
    "QuickBlox-messages": "External", 
    "QuickBlox-chat": "External", 
    "Google-Play-Services-Tasks": "AndroidDev", 
    "Parse.com": "External", 
    "AirMapView": "External", 
    "Box-Share-SDK": "External", 
    "MoPub": "Advertising", 
    "Amazon-SimpleDB": "External", 
    "Google-Play-Services-Gass": "AndroidDev", 
    "Google-Play-Services-Wallet": "AndroidDev", 
    "MoPub-native-static": "Advertising", 
    "Guice": "AndroidUtil", 
    "HockeyApp": "Analytics", 
    "MaterialEditText": "AndroidUtil", 
    "Amazon-Simple-Email-Service-(SES)": "External", 
    "Facebook-Sharing": "SocialMedia", 
    "Amazon-AWS-Key-Management-Service-(KMS)": "External", 
    "IOCipher": "Extension", 
    "Guava": "Extension", 
    "android-oauth-client": "Network", 
    "Retrolambda": "Extension", 
    "roboguice": "AndroidUtil", 
    "Appsfire": "Advertising", 
    "QuickBlox-customobjects": "External", 
    "Apache-HttpClient-for-Android": "Network", 
    "TrustedIntents": "AndroidUtil", 
    "flickrj": "SocialMedia", 
    "Amazon-AWS-Mobile-SDK-core": "External", 
    "AndroidAsync": "Network", 
    "Firebase-Crash": "AndroidUtil", 
    "Google-Play-Services-Analytics-Impl": "AndroidDev", 
    "QuickBlox-core": "External", 
    "Pinterest": "SocialMedia", 
    "Fresco": "Image", 
    "Amazon-AWS-Elastic-Beanstalk": "External", 
    "ExoPlayer": "AndroidUtil", 
    "Google-Play-Services-Auth": "AndroidDev", 
    "Picasso": "Image", 
    "MoPub-interstitial": "Advertising", 
    "QuickBlox-content": "External", 
    "Twitter4J": "SocialMedia", 
    "Google-Play-Services-Nearby": "AndroidDev", 
    "Supersonic": "Advertising", 
    "TapIt": "Advertising", 
    "Amazon-AWS-Mobile-Analytics": "Analytics", 
    "PrettyTime": "Extension", 
    "AMoAd": "Advertising", 
    "Google-Play-Services-Cast": "AndroidDev", 
    "Android-support-v7-appcompat": "AndroidDev", 
    "ironSource": "Advertising", 
    "Google-Play-Services-Vision": "AndroidDev", 
    "Amazon-Polly": "External", 
    "log4j": "Util", 
    "NetCipher-httpclient": "Network", 
    "Tape": "Extension", 
    "android-gif-drawable": "Image", 
    "Facebook-Messenger": "SocialMedia", 
    "Amazon-AWS-IoT": "External", 
    "Material-Calendar-View": "AndroidUtil", 
    "OrmLite": "Util", 
    "Facebook-Core": "SocialMedia", 
    "PubNub": "External", 
    "Millennial-Media": "Advertising", 
    "Vdopia": "Advertising", 
    "Google-Play-Services-Fitness": "AndroidDev", 
    "OkHttp": "Network", 
    "PNGJ": "Image", 
    "Chartboost": "Advertising", 
    "Google-Play-Services-Iid": "AndroidDev", 
    "Retrofit": "Network", 
    "Google-Play-Services-Auth-Base": "AndroidDev", 
    "Amazon-AWS-Lambda": "External", 
    "vkontakte": "SocialMedia", 
    "Google-Play-Services-Contextmanager": "AndroidDev", 
    "CleverTap": "External", 
    "LinkedIn": "SocialMedia", 
    "Amazon-DynamoDB-Document": "External", 
    "Stetho": "AndroidUtil", 
    "signpost": "Network", 
    "ORMLite-JDBC": "Util", 
    "MdotM": "Advertising", 
    "LG-U+AD": "Advertising", 
    "AppBrain": "Advertising", 
    "Box-Preview-SDK": "External", 
    "TwitterCore": "SocialMedia", 
    "Firebase-Analytics": "Analytics", 
    "Amazon-API-Gateway": "External", 
    "RxAndroid": "Extension", 
    "Facebook-Places": "SocialMedia", 
    "Apache-Commons-Collections": "Extension", 
    "Urban-Airship": "Analytics", 
    "Pollfish": "Advertising", 
    "Android-support-v4": "AndroidDev", 
    "Google-Play-Services": "AndroidDev", 
    "NetCipher-chboye": "Network", 
    "Amazon-Rekognition": "External", 
    "Dropbox": "External", 
    "Amazon-Cognito-Auth": "External", 
    "universal-image-loader": "Image", 
    "Ticker": "AndroidUtil", 
    "Gson": "Util", 
    "Logger": "Util", 
    "Amazon-Simple-Storage-Service-(S3)": "External", 
    "Amazon-Cloud-Watch": "External", 
    "MoPub-rewardedvideo": "Advertising", 
    "Apache-James-Mime4J": "Util", 
    "smaato": "Advertising", 
    "GeoJSON": "Util", 
    "Google-Admob": "Advertising", 
    "TrustKit": "Util", 
    "MoPub-base": "Advertising", 
    "WeChat": "SocialMedia", 
    "QuickBlox-videochat": "External", 
    "Android-support-v13": "AndroidDev", 
    "Google-Play-Services-Places": "AndroidDev", 
    "Box-Content-SDK": "External", 
    "New-Relic": "AndroidUtil", 
    "TimesSquare": "AndroidUtil", 
    "Box-Browse-SDK": "External", 
    "Airpush-(Universal)": "Advertising", 
    "Amazon-Maps": "External", 
    "Butter-Knife": "AndroidUtil", 
    "Apache-Commons-Lang": "Extension", 
    "Google-Play-Services-All-Wear": "AndroidDev", 
    "Google-Maps-for-Work": "External", 
    "ACRA": "AndroidUtil", 
    "Fyber": "Advertising", 
    "Facebook-Login": "SocialMedia", 
    "mapsforge": "Util", 
    "AdColony": "Advertising", 
    "Apache-Commons-IO": "Extension"
}
